tbsfusion/__init__.py
tbsfusion/tbs_fusion.py
tbs_fusion_py-1.0.0.dist-info/LICENSE
tbs_fusion_py-1.0.0.dist-info/METADATA
tbs_fusion_py-1.0.0.dist-info/WHEEL
tbs_fusion_py-1.0.0.dist-info/top_level.txt
tbs_fusion_py-1.0.0.dist-info/RECORD
