Metadata-Version: 2.1
Name: tbs-fusion-py
Version: 1.0.0
Summary: A Python package to control the TBS Fusion analog video receiver module over a serial connection.
Author-email: Martin Luessi <mluessi@gmail.com>
Project-URL: Homepage, https://github.com/BrainFPV/tbs-fusion-py
Project-URL: Issues, https://github.com/BrainFPV/tbs-fusion-py/issues
Classifier: Programming Language :: Python :: 3
Classifier: License :: OSI Approved :: BSD License
Classifier: Operating System :: OS Independent
Requires-Python: >=3.8
License-File: LICENSE
Requires-Dist: pyserial >=3.5
Requires-Dist: pycrc >=0.10.0
